{
  "amazfit.com": {
    "rank": "51",
    "private": [],
    "third": [
      "ALIBABA"
    ]
  },
  "gionee.com": {
    "rank": "52",
    "private": [],
    "third": [
      "ALIBABA"
    ]
  },
  "nubia.cn": {
    "rank": "53",
    "private": [],
    "third": [
      "hichina.com"
    ]
  },
  "tanx.com": {
    "rank": "54",
    "private": [
      "ALIBABA"
    ],
    "third": []
  },
  "autonavi.com": {
    "rank": "55",
    "private": [],
    "third": [
      "ALIBABA"
    ]
  },
  "iamh5.cn": {
    "rank": "56",
    "private": [],
    "third": [
      "hichina.com"
    ]
  },
  "netease.com": {
    "rank": "57",
    "private": [
      "nease.net"
    ],
    "third": [
      "166.com"
    ]
  },
  "the9.com": {
    "rank": "58",
    "private": [
      "the9.com"
    ],
    "third": []
  },
  "sohu.com.cn": {
    "rank": "59",
    "private": [
      "sohu.com"
    ],
    "third": []
  },
  "iqiyi.com": {
    "rank": "60",
    "private": [
      "iqiyi.com"
    ],
    "third": []
  }
}