{
  "aizhan.com": {
    "rank": "901",
    "private": {
      "https://statics.aizhan.com/js/script.js?v=0304": 2
    },
    "third": {}
  },
  "zbj.com": {
    "rank": "902",
    "private": {},
    "third": {}
  },
  "alibaba.com": {
    "rank": "903",
    "private": {
      "https://www.alibaba.com/": 52,
      "https://g.alicdn.com/bc/home-col-right/0.0.4/js/index.js": 20,
      "https://retcode.alicdn.com/retcode/bl.js": 165,
      "https://i.alicdn.com/??sc-global/atom.d6f017ad.js,sc-affiliate/hashmap.76e9be26.js": 135,
      "https://s.alicdn.com/@g/icbu-group/??icbu-globaljs-config/0.0.64/main.js,icbu-globaljs/0.1.4/global.min.js": 16,
      "https://s.alicdn.com/@g/sc/image-upload-react/0.0.2/202212-image-hack.bundle.js": 1,
      "https://i.alicdn.com/??sc-global-components/20190221151643/entrances/trade-alert/standalone/trade-alert.js,sc-global-components/20200928154656/entrances/xman/xman.js,sc-global-components/20180719155510/entrances/link-tab-control/link-tab-control.js": 30,
      "https://assets.alicdn.com/g/alilog/??aplus_plugin_icbufront/index.js,mlog/aplus_v2.js": 36,
      "https://i.alicdn.com/??sc-global-components/20190619152737/entrances/big-brother/big-brother.js": 4,
      "https://insights.alibaba.com/openservice/gatewayService?modelId=835&appName=asinHomePage&callback=isNewUserCallback": 1,
      "https://s.alicdn.com/@g/sc/aisn/0.0.118/??sc-aisn/hashmap.js,sc-aisn/home2019/common.js,sc-aisn/home2019/home.js": 44,
      "https://i.alicdn.com/sc-global/base/package.8012284b.js": 39,
      "https://s.alicdn.com/@g/msite/gdpr-cookie-notice/0.0.9/index.js": 6,
      "https://s.alicdn.com/@g/sc/header-footer/0.1.3/sc-header-footer/header/entrances/global-header-new/header.js": 77,
      "https://s.alicdn.com/@g/flasher/sw/2.13.21/client/index.js": 115,
      "https://insights.alibaba.com/openservice/gatewayService?appKey=vee8meczxjj3hugfjlmg0t4zh4skimd3&appName=asinHomePage&callback=__jp74285&modelId=1229": 1,
      "https://aeis.alicdn.com/AWSC/AWSC/awsc.js": 6,
      "https://s.alicdn.com/@g/sc-assets/bz-evaluate/0.0.63/pages/survey/index.web.js": 215,
      "https://marketing.alibaba.com/queryNicheMaterial.do?nicheCode=ICBU_PC_HEADER_PROMOTION_ATMOSPHERE&callback=headerPromotionCallback": 1,
      "https://s.alicdn.com/@g/sc/home-aisn/0.0.26/pages/index.js": 765,
      "https://is.alicdn.com/js/6v/biz/common/store-proxy/store-proxy2.html?iframe_delete=true": 1,
      "https://s.alicdn.com/@g/sc/global-components/??1.0.4/sc-global-components/entrances/loader.js": 5,
      "https://aeis.alicdn.com/AWSC/WebUMID/1.92.0/um.js": 13,
      "https://g.alicdn.com/alilog/mlog/aplus_v2.js": 17,
      "https://i.alicdn.com/??sc-global-components/20190313110207/entrances/top-banner/top-banner.js": 3,
      "https://assets.alicdn.com/g/sd/baxia-entry/index.js?t=232395": 4,
      "https://assets.alicdn.com/g/secdev/entry/index.js?t=232395": 9,
      "https://s.alicdn.com/@g/sc/header-footer/0.1.3/sc-header-footer/header/entrances/defer-common/defer-common.js": 31,
      "https://assets.alicdn.com/g/alilog/s/8.15.21/plugin/aplus_ae.js": 28,
      "https://assets.alicdn.com/g??xlly/spl/rp.js,secdev/nsv/1.0.87/ns_f_95_3_f.js?v=1": 27,
      "https://g.alicdn.com/sd/baxia-entry/index.js?t=232395": 4,
      "https://g.alicdn.com/secdev/entry/index.js?t=232395": 9,
      "https://g.alicdn.com/??xlly/spl/rp.js,secdev/nsv/1.0.87/ns_f_95_3_f.js?v=1": 2,
      "https://assets.alicdn.com/g/sd/baxia/2.2.3/baxiaCommon.js": 24,
      "https://assets.alicdn.com/g/secdev/sufei_data/3.9.10/index.js": 25,
      "https://assets.alicdn.com/g/AWSC/et/1.62.7/et_f.js": 25,
      "https://s.alicdn.com/@g/icbu-fe-arch/network-speed/0.0.1/discover.js": 2,
      "https://i.alicdn.com/sc-global-components/20171026105532/entrances/third-part-login/third-part-login.js": 6,
      "https://i.alicdn.com/sc-affiliate/sem-remarketing/??sem-remarketing.98174a0b.js": 9,
      "https://offer.alibaba.com/product/fetchSiteTag.jsonp?siteName=home&pageFrom=home&pageInfo=%7B%22pageType%22%3A%22home%22%2C%22siteName%22%3A%22home%22%2C%22isP4P%22%3Afalse%2C%22pageDevice%22%3A%22PC%22%7D&language=&callback=jsonp_167324558596946427": 1,
      "https://i.alicdn.com/sc-affiliate/sem-remarketing/proxy.8144c682.html?iframe_delete=true": 9
    },
    "third": {
      "https://s.yimg.com/wi/ytc.js": 7,
      "https://connect.facebook.net/en_US/fbevents.js": 33
    }
  },
  "haiwainet.cn": {
    "rank": "904",
    "private": {
      "http://statics.haiwainet.cn/js/index_js/tongji.js": 9,
      "http://www.haiwainet.cn/": 7,
      "http://statics.haiwainet.cn/js/baiduad.js": 22,
      "http://statics.haiwainet.cn/js/common_js/jquery-1.11.2.min.js": 6,
      "http://statics.haiwainet.cn/tpl2021/2021-03-20/js/index.js": 2,
      "http://statics.haiwainet.cn/html/adIframe.html?adfn=7497867,,300,70,,inlay-fix,,ad_lbhh2b69qe": 4,
      "http://statics.haiwainet.cn/html/adIframe.html?adfn=7497864,,1200,100,,inlay-fix,,ad_abkifwbhedi": 4,
      "http://statics.haiwainet.cn/html/adIframe.html?adfn=7497865,,1200,100,,inlay-fix,,ad_u0smjoji0xb": 4,
      "http://statics.haiwainet.cn/html/adIframe.html?adfn=7497866,,300,70,,inlay-fix,,ad_uaj0dezpov": 4,
      "http://statics.haiwainet.cn/html/adIframe.html?adfn=7499941,,350,180,,inlay-fix,,ad_4wfvzhvncjn": 4
    },
    "third": {
      "https://tags.creativecdn.com/MeMnnO3Z4y1ZJNJMYuRf.js": 4,
      "https://retcode.alicdn.com/retcode/bl.js": 29,
      "https://shop-cart.app/_product.ja": 1,
      "https://cdn.dsncdn.com/analytics.popper.min.js": 2,
      "https://webtrafficsource.com/js/v1/rtg.js": 2,
      "http://cl2.webterren.com/webdig.js?z=15": 2,
      "https://d.alicdn.com/alilog/mlog/aplus/203467608.js": 50,
      "http://pos.baidu.com/ecem?di=7497864&dri=0&dis=3&dai=0&ps=0x0&enu=encoding&dcb=baidu_595e1pllz8q&dtm=SSP_JSONP&dvi=0.0&dci=-1&dpt=none&tsr=0&tpr=1526036151662&ari=2&dbv=2&drs=1&pcs=980x90&pss=980x90&cfv=0&cpl=5&chi=1&cce=true&cec=windows-1252&tlm=1526035334&rw=320&ltu=http%3A%2F%2Fcms.haiwainet.com.cn%2Findex.php%3Fm%3Dcontent%26c%3Dindex%26a%3Dlists%26job%3Dpreview%26catid%3D232657&liu=http%3A%2F%2Fstatics.haiwainet.cn%2Fhtml%2FadIframe.html%3Fadfn%3D5595932%2C%2C980%2C90%2C%2Cinlay-fix&ltr=http%3A%2F%2Fcms.haiwainet.com.cn%2Findex.php%3Fm%3Dcontent%26c%3Dindex%26a%3Dlists%26job%3Dpreview%26catid%3D232657&lcr=http%3A%2F%2Fcms.haiwainet.com.cn%2Findex.php%3Fm%3Dcontent%26c%3Dindex%26a%3Dlists%26job%3Dpreview%26catid%3D232657&ecd=1&uc=2517x1417&pis=980x90&sr=2560x1440&tcn=1526036152&lto=http%3A%2F%2Fcms.haiwainet.com.cn&ltl=1": 1,
      "http://pos.baidu.com/ecem?di=7497865&dri=0&dis=3&dai=0&ps=0x0&enu=encoding&dcb=baidu_bz0sgoofff&dtm=SSP_JSONP&dvi=0.0&dci=-1&dpt=none&tsr=0&tpr=1526036151662&ari=2&dbv=2&drs=1&pcs=980x90&pss=980x90&cfv=0&cpl=5&chi=1&cce=true&cec=windows-1252&tlm=1526035334&rw=320&ltu=http%3A%2F%2Fcms.haiwainet.com.cn%2Findex.php%3Fm%3Dcontent%26c%3Dindex%26a%3Dlists%26job%3Dpreview%26catid%3D232657&liu=http%3A%2F%2Fstatics.haiwainet.cn%2Fhtml%2FadIframe.html%3Fadfn%3D5595932%2C%2C980%2C90%2C%2Cinlay-fix&ltr=http%3A%2F%2Fcms.haiwainet.com.cn%2Findex.php%3Fm%3Dcontent%26c%3Dindex%26a%3Dlists%26job%3Dpreview%26catid%3D232657&lcr=http%3A%2F%2Fcms.haiwainet.com.cn%2Findex.php%3Fm%3Dcontent%26c%3Dindex%26a%3Dlists%26job%3Dpreview%26catid%3D232657&ecd=1&uc=2517x1417&pis=980x90&sr=2560x1440&tcn=1526036152&lto=http%3A%2F%2Fcms.haiwainet.com.cn&ltl=1": 1,
      "http://pos.baidu.com/ecem?di=7497867&dri=0&dis=3&dai=0&ps=0x0&enu=encoding&dcb=baidu_nganfgwn2aq&dtm=SSP_JSONP&dvi=0.0&dci=-1&dpt=none&tsr=0&tpr=1526036151662&ari=2&dbv=2&drs=1&pcs=980x90&pss=980x90&cfv=0&cpl=5&chi=1&cce=true&cec=windows-1252&tlm=1526035334&rw=320&ltu=http%3A%2F%2Fcms.haiwainet.com.cn%2Findex.php%3Fm%3Dcontent%26c%3Dindex%26a%3Dlists%26job%3Dpreview%26catid%3D232657&liu=http%3A%2F%2Fstatics.haiwainet.cn%2Fhtml%2FadIframe.html%3Fadfn%3D5595932%2C%2C980%2C90%2C%2Cinlay-fix&ltr=http%3A%2F%2Fcms.haiwainet.com.cn%2Findex.php%3Fm%3Dcontent%26c%3Dindex%26a%3Dlists%26job%3Dpreview%26catid%3D232657&lcr=http%3A%2F%2Fcms.haiwainet.com.cn%2Findex.php%3Fm%3Dcontent%26c%3Dindex%26a%3Dlists%26job%3Dpreview%26catid%3D232657&ecd=1&uc=2517x1417&pis=980x90&sr=2560x1440&tcn=1526036152&lto=http%3A%2F%2Fcms.haiwainet.com.cn&ltl=1": 1,
      "http://pos.baidu.com/ecem?di=7497866&dri=0&dis=3&dai=0&ps=0x0&enu=encoding&dcb=baidu_ynb8q472vrp&dtm=SSP_JSONP&dvi=0.0&dci=-1&dpt=none&tsr=0&tpr=1526036151662&ari=2&dbv=2&drs=1&pcs=980x90&pss=980x90&cfv=0&cpl=5&chi=1&cce=true&cec=windows-1252&tlm=1526035334&rw=320&ltu=http%3A%2F%2Fcms.haiwainet.com.cn%2Findex.php%3Fm%3Dcontent%26c%3Dindex%26a%3Dlists%26job%3Dpreview%26catid%3D232657&liu=http%3A%2F%2Fstatics.haiwainet.cn%2Fhtml%2FadIframe.html%3Fadfn%3D5595932%2C%2C980%2C90%2C%2Cinlay-fix&ltr=http%3A%2F%2Fcms.haiwainet.com.cn%2Findex.php%3Fm%3Dcontent%26c%3Dindex%26a%3Dlists%26job%3Dpreview%26catid%3D232657&lcr=http%3A%2F%2Fcms.haiwainet.com.cn%2Findex.php%3Fm%3Dcontent%26c%3Dindex%26a%3Dlists%26job%3Dpreview%26catid%3D232657&ecd=1&uc=2517x1417&pis=980x90&sr=2560x1440&tcn=1526036152&lto=http%3A%2F%2Fcms.haiwainet.com.cn&ltl=1": 1,
      "http://pos.baidu.com/ecem?di=7499941&dri=0&dis=3&dai=0&ps=0x0&enu=encoding&dcb=baidu_pp5r3lq5orl&dtm=SSP_JSONP&dvi=0.0&dci=-1&dpt=none&tsr=0&tpr=1526036151662&ari=2&dbv=2&drs=1&pcs=980x90&pss=980x90&cfv=0&cpl=5&chi=1&cce=true&cec=windows-1252&tlm=1526035334&rw=320&ltu=http%3A%2F%2Fcms.haiwainet.com.cn%2Findex.php%3Fm%3Dcontent%26c%3Dindex%26a%3Dlists%26job%3Dpreview%26catid%3D232657&liu=http%3A%2F%2Fstatics.haiwainet.cn%2Fhtml%2FadIframe.html%3Fadfn%3D5595932%2C%2C980%2C90%2C%2Cinlay-fix&ltr=http%3A%2F%2Fcms.haiwainet.com.cn%2Findex.php%3Fm%3Dcontent%26c%3Dindex%26a%3Dlists%26job%3Dpreview%26catid%3D232657&lcr=http%3A%2F%2Fcms.haiwainet.com.cn%2Findex.php%3Fm%3Dcontent%26c%3Dindex%26a%3Dlists%26job%3Dpreview%26catid%3D232657&ecd=1&uc=2517x1417&pis=980x90&sr=2560x1440&tcn=1526036152&lto=http%3A%2F%2Fcms.haiwainet.com.cn&ltl=1": 1,
      "http://dup.baidustatic.com/js/ds.js": 50,
      "http://sofire.bdstatic.com/js/dfxaf3-635b4cd6.js": 45
    }
  },
  "leancloud.cn": {
    "rank": "905",
    "private": {},
    "third": {
      "https://www.googletagmanager.com/gtag/js?id=UA-42629236-1": 17,
      "https://www.google-analytics.com/analytics.js": 18,
      "https://www.googletagmanager.com/gtag/js?id=AW-1030743864&l=dataLayer&cx=c": 20
    }
  },
  "gf.com.cn": {
    "rank": "906",
    "private": {
      "http://www.gf.com.cn/": 4
    },
    "third": {}
  },
  "95516.com": {
    "rank": "907",
    "private": {
      "http://www.95516.com/pc/js/vendor.js": 4,
      "https://device.95516.com/analytics/walletvm/scripts/behaviorcollect2.js": 2,
      "https://device.95516.com/analytics/walletvm/scripts/bh_sensors.js?v=202110191419": 2
    },
    "third": {}
  },
  "inditex.com": {
    "rank": "908",
    "private": {},
    "third": {}
  },
  "qqtn.com": {
    "rank": "909",
    "private": {
      "https://www.qqtn.com/skin/know/count.js": 2,
      "https://www.qqtn.com/skin/new2018/js/jqbs.main.js": 10,
      "https://www.qqtn.com/skin/new2018/js/index2018.js": 1
    },
    "third": {}
  },
  "windowsphone.com": {
    "rank": "910",
    "private": {},
    "third": {}
  },
  "911cha.com": {
    "rank": "911",
    "private": {},
    "third": {}
  },
  "duba.com": {
    "rank": "912",
    "private": {
      "https://www.duba.com/": 2,
      "https://www.duba.com/static/v4/home/js/main.cb1ff153.js": 81,
      "https://www.duba.com/static/v4/home/js/chunk-vendors.7d79461c.js": 140,
      "https://www.duba.com/static/v4/home/js/jquery.min.2.2.4.js": 14,
      "https://www.duba.com/proxy/tj/home?st=__proxy&site=dh123&type=https": 8,
      "https://cdndownload.liehu.ijinshan.com/liehu/static/pcad-sdk/bin/orion-pcad-sdk-0.0.3.min.js": 5
    },
    "third": {
      "https://act.cmcmcdn.com/cmnews-sdk/0.4.3/cmnews-sdk.umd.js": 6,
      "https://w.cnzz.com/c.php?id=30069637&l=3": 4
    }
  },
  "21cn.com": {
    "rank": "913",
    "private": {},
    "third": {}
  },
  "tuliu.com": {
    "rank": "914",
    "private": {
      "https://www.tuliu.com/": 5,
      "https://swt.tuliu.com/JS/LsJS.aspx?siteid=KMY37609310&float=0&lng=cn": 1,
      "https://statics.tuliu.com/web/js/vendor/vendor.min.js?ver=VV20220919101103": 18,
      "https://statics.tuliu.com/web/js/business/index_new.js?ver=VV20220919101103": 2
    },
    "third": {
      "http://www.21cn.com/": 2,
      "http://www.21cn.com/js/vendors.899155c3.js": 187,
      "http://www.21cn.com/js/app.f70373d4.js": 29
    }
  },
  "babybus.com": {
    "rank": "915",
    "private": {
      "https://www.babybus.com/js/greySwitch.js": 1,
      "https://www.babybus.com/js/babybus_analysis.js": 39,
      "https://www.babybus.com/js/bbAnalysis.js": 2,
      "https://www.babybus.com/js/googleGtag.js": 18,
      "https://www.babybus.com/js/googleRecord.js": 2,
      "https://www.babybus.com/js/hmt.js": 2,
      "https://www.babybus.com/_nuxt/b91742c.js": 1,
      "https://www.babybus.com/_nuxt/35a5929.js": 12,
      "https://www.babybus.com/_nuxt/e04239a.js": 100,
      "https://www.babybus.com/_nuxt/6717de6.js": 1
    },
    "third": {}
  },
  "inmobi.com": {
    "rank": "916",
    "private": {
      "https://www.inmobi.com/": 3,
      "https://www.inmobi.com/_next/static/chunks/framework.c1af385086505ff32f23.js": 207,
      "https://www.inmobi.com/_next/static/chunks/main-ccf0bf42cc2c52193732.js": 176,
      "https://www.inmobi.com/_next/static/chunks/3e9d04194c76d0abb7e1565c649b8e65d865d789.aa31df0a5f21ed5c9d93.js": 96,
      "https://www.inmobi.com/_next/static/chunks/9eeab56ec6136efd84e8a9b86d2dcecf2deb6509.f4ce196ed393c084c4b9.js": 4
    },
    "third": {
      "https://www.babybus.com/js/googleGtag.js": 4,
      "https://www.googletagmanager.com/gtm.js?id=GTM-MJ2BNZG": 221,
      "https://snap.licdn.com/li.lms-analytics/insight.min.js": 2,
      "https://www.google-analytics.com/analytics.js": 9,
      "https://bat.bing.com/bat.js": 3,
      "https://az416426.vo.msecnd.net/scripts/b/ai.2.min.js": 22,
      "https://snap.licdn.com/li.lms-analytics/insight.old.min.js": 25,
      "https://s.adroll.com/j/BFXZZVIWPZER3NIYOLIHZ3/roundtrip.js": 33,
      "https://connect.facebook.net/en_US/fbevents.js": 27,
      "https://js.hs-scripts.com/2714195.js": 10,
      "https://www.googletagmanager.com/gtag/js?id=G-9JNJRHH1VL&l=dataLayer&cx=c": 23,
      "https://js.hscollectedforms.net/collectedforms.js": 3,
      "https://js.hs-banner.com/2714195.js": 15,
      "https://d.adroll.com/consent/check/BFXZZVIWPZER3NIYOLIHZ3?pv=42127054951.6279&arrfrr=https%3A%2F%2Fwww.inmobi.com%2F&_s=99b487d516177f5358efbab4314aae5e&_b=2": 3,
      "https://connect.facebook.net/signals/config/200663993809923?v=2.9.91&r=stable": 2,
      "https://js.hsforms.net/forms/v2.js": 9
    }
  },
  "wpengine.com": {
    "rank": "917",
    "private": {
      "https://wpengine.com/wp-content/mu-plugins/wpengine-library/js/main.js?ver=1666297500": 2
    },
    "third": {
      "https://inmobi.widget.insent.ai/insent": 2,
      "https://inmobi.widget.insent.ai/static/js/vendors.c0a09fe3.js": 9,
      "https://az416426.vo.msecnd.net/scripts/b/ai.2.min.js": 15,
      "https://js.hsleadflows.net/leadflows.js": 3
    }
  },
  "buzzfeed.com": {
    "rank": "918",
    "private": {
      "https://www.buzzfeed.com/": 5,
      "https://www.buzzfeed.com/static-assets/bf-homepage-ui/_next/static/chunks/pages/_app-261e1919be15abd1.js": 104,
      "https://www.buzzfeed.com/static-assets/bf-homepage-ui/_next/static/chunks/webpack-429b84ef219675df.js": 3,
      "https://www.buzzfeed.com/static-assets/bf-homepage-ui/_next/static/chunks/699-89e531855075d3fa.js": 19,
      "https://www.buzzfeed.com/static-assets/bf-homepage-ui/_next/static/chunks/pages/index-e6f27ede00e01ad9.js": 2,
      "https://www.buzzfeed.com/static-assets/bf-homepage-ui/_next/static/chunks/framework-348f86d225132ea3.js": 158,
      "https://www.buzzfeed.com/static-assets/bf-homepage-ui/_next/static/chunks/main-651b3fde0eea7f85.js": 201,
      "https://www.buzzfeed.com/static-assets/bf-homepage-ui/_next/static/chunks/705-9c1c11dd52f39f3a.js": 66,
      "https://www.buzzfeed.com/static-assets/bf-homepage-ui/_next/static/chunks/611-9a5afa772829718c.js": 2
    },
    "third": {
      "https://static.chartbeat.com/js/chartbeat_mab.js": 3,
      "https://www.googletagmanager.com/gtm.js?id=GTM-55L29GF": 14,
      "https://www.google-analytics.com/analytics.js": 18,
      "https://www.google-analytics.com/plugins/ua/linkid.js": 3,
      "https://cdn.permutive.com/6ef7b2c1-fe43-45ad-8551-5377c13e2f71-web.js": 143,
      "https://asset.fwpub1.com/js/embed-feed.js": 84,
      "https://securepubads.g.doubleclick.net/tag/js/gpt.js": 7,
      "https://cmp.quantcast.com/choice/3aud4J6uA4Z6Y/www.buzzfeed.com/choice.js?timestamp=1673246088625": 3,
      "https://tagan.adlightning.com/buzzfeed/op.js": 17,
      "https://pub.doubleverify.com/signals/pub.js": 33,
      "https://c.amazon-adsystem.com/aax2/apstag.js": 27,
      "https://a.teads.tv/analytics/tag.js": 2,
      "https://connect.facebook.net/en_US/fbevents.js": 27,
      "https://securepubads.g.doubleclick.net/gpt/pubads_impl_2022120801.js": 44,
      "https://tags.crwdcntrl.net/lt/c/16576/sync.min.js": 9,
      "https://ats.rlcdn.com/ats.js": 5,
      "https://cdn.id5-sync.com/api/1.0/id5-api.js": 17,
      "https://quantcast.mgr.consensu.org/tcfv2/43/cmp2.js?referer=www.buzzfeed.com": 12,
      "https://connect.facebook.net/signals/config/260954170738952?v=2.9.91&r=stable": 58,
      "https://tpc.googlesyndication.com/sodar/sodar2.js": 61,
      "https://tpc.googlesyndication.com/sodar/sodar2/225/runner.html": 27
    }
  },
  "scarabresearch.com": {
    "rank": "919",
    "private": {},
    "third": {
      "https://www.buzzfeed.com/static-assets/bf-homepage-ui/_next/static/chunks/705-9c1c11dd52f39f3a.js": 1,
      "https://www.buzzfeed.com/static-assets/bf-homepage-ui/_next/static/chunks/pages/_app-261e1919be15abd1.js": 1
    }
  },
  "camera360.com": {
    "rank": "920",
    "private": {
      "https://www.camera360.com/_nuxt/0a226d3.js": 1,
      "https://www.camera360.com/_nuxt/e23d5a6.js": 1,
      "https://www.camera360.com/_nuxt/da924ee.js": 4,
      "https://www.camera360.com/_nuxt/0cd032d.js": 17
    },
    "third": {}
  },
  "ztgame.com.cn": {
    "rank": "921",
    "private": {
      "http://www.ztgame.com.cn/": 3
    },
    "third": {
      "https://mtm.zt-g.com/js/container_KWo2eSBv.js": 24
    }
  },
  "39.net": {
    "rank": "922",
    "private": {
      "http://www.39.net/": 4,
      "https://static.39.net/pub/xyz/style.js": 84,
      "http://d-test.39.net/20160105?pv=1&sp=22090,1,0,0,0,1,1,0&ec=UTF-8&re=1920,1080&jsv=7&cb=4059708988&seq=2&fs=1": 2,
      "http://d-test.39.net/20160105?pv=1&sp=23051,1,0,0,0,1,1,0&ec=UTF-8&re=1920,1080&jsv=7&cb=6437955295&seq=7&fs=6": 3,
      "http://d-test.39.net/20160105?pv=1&sp=23052,1,0,0,0,1,1,0&ec=UTF-8&re=1920,1080&jsv=7&cb=5275259945&seq=8&fs=8": 6,
      "https://image.39.net/tools/djan.js": 7,
      "http://image.39.net/tools/3.js": 1,
      "https://static.39.net/lib/jquery/core/jquery-1.8.3.min.js": 6,
      "https://static.39.net/pub/www/v2019/pc/index/js/39index2019_common.js": 1
    },
    "third": {
      "https://hm.baidu.com/hm.js?9840601cb51320c55bca4fa0f4949efe": 5,
      "http://hm.baidu.com/hm.js?ab2e5965345c61109c5e97c34de8026a": 3,
      "http://cpro.baidustatic.com/cpro/ui/cm.js": 71,
      "http://sofire.bdstatic.com/js/dfxaf3-635b4cd6.js": 9,
      "https://pos.baidu.com/bcvm?di=u6055253&uuid=ed7d18a0f27f791c&dri=0&dis=0&dai=2&ps=3143x0&enu=encoding&exps=110011&ant=0&psi=090d9c18b02ac805&dcb=___adblockplus_&dtm=SSP_JSONP&dvi=0.0&dci=-1&dpt=none&tpr=1673246195641&ti=39%E5%81%A5%E5%BA%B7%E7%BD%91_%E4%B8%AD%E5%9B%BD%E4%BC%98%E8%B4%A8%E5%8C%BB%E7%96%97%E4%BF%9D%E5%81%A5%E4%BF%A1%E6%81%AF%E4%B8%8E%E5%9C%A8%E7%BA%BF%E5%81%A5%E5%BA%B7%E6%9C%8D%E5%8A%A1%E5%B9%B3%E5%8F%B0&ari=2&ver=1221&dbv=2&drs=1&pcs=785x585&pss=1200x4673&cfv=0&cpl=0&chi=50&cce=true&cec=UTF-8&tlm=1673246195&prot=2&rw=600&ltu=http%3A%2F%2Fwww.39.net%2F&ecd=1&dft=0&uc=1920x1055&pis=-1x-1&sr=1920x1080&tcn=1673246196": 1,
      "https://pos.baidu.com/bcvm?di=u6055252&uuid=e5f7573edafdda6e&dri=0&dis=0&dai=1&ps=3143x0&enu=encoding&exps=110011&ant=0&psi=090d9c18b02ac805&dcb=___adblockplus_&dtm=SSP_JSONP&dvi=0.0&dci=-1&dpt=none&tpr=1673246195641&ti=39%E5%81%A5%E5%BA%B7%E7%BD%91_%E4%B8%AD%E5%9B%BD%E4%BC%98%E8%B4%A8%E5%8C%BB%E7%96%97%E4%BF%9D%E5%81%A5%E4%BF%A1%E6%81%AF%E4%B8%8E%E5%9C%A8%E7%BA%BF%E5%81%A5%E5%BA%B7%E6%9C%8D%E5%8A%A1%E5%B9%B3%E5%8F%B0&ari=2&ver=1221&dbv=2&drs=1&pcs=785x585&pss=1200x4673&cfv=0&cpl=0&chi=50&cce=true&cec=UTF-8&tlm=1673246195&prot=2&rw=600&ltu=http%3A%2F%2Fwww.39.net%2F&ecd=1&dft=0&uc=1920x1055&pis=-1x-1&sr=1920x1080&tcn=1673246196": 1,
      "https://pos.baidu.com/bcvm?conwid=600&conhei=90&rdid=6055253&dc=3&di=u6055253&s1=3984398496&s2=4068440348&dri=0&dis=0&dai=2&ps=3143x0&enu=encoding&exps=110277,110275,110261,110252,110011&ant=0&psi=090d9c18b02ac805&dcb=___adblockplus_&dtm=HTML_POST&dvi=0.0&dci=-1&dpt=none&tpr=1673246195641&ti=39%E5%81%A5%E5%BA%B7%E7%BD%91_%E4%B8%AD%E5%9B%BD%E4%BC%98%E8%B4%A8%E5%8C%BB%E7%96%97%E4%BF%9D%E5%81%A5%E4%BF%A1%E6%81%AF%E4%B8%8E%E5%9C%A8%E7%BA%BF%E5%81%A5%E5%BA%B7%E6%9C%8D%E5%8A%A1%E5%B9%B3%E5%8F%B0&ari=2&ver=1221&dbv=2&drs=1&pcs=785x585&pss=1200x4673&cfv=0&cpl=0&chi=50&cce=true&cec=UTF-8&tlm=1673246195&prot=2&rw=600&ltu=http%3A%2F%2Fwww.39.net%2F&ecd=1&dft=0&uc=1920x1055&pis=-1x-1&sr=1920x1080&tcn=1673246196&qn=a36ec8ce13290fae&ft=1": 5,
      "https://pos.baidu.com/bcvm?di=u6055282&uuid=c1dcb769bf314c23&dri=0&dis=0&dai=4&ps=4673x0&enu=encoding&exps=110011&ant=0&psi=090d9c18b02ac805&dcb=___adblockplus_&dtm=SSP_JSONP&dvi=0.0&dci=-1&dpt=none&tpr=1673246195641&ti=39%E5%81%A5%E5%BA%B7%E7%BD%91_%E4%B8%AD%E5%9B%BD%E4%BC%98%E8%B4%A8%E5%8C%BB%E7%96%97%E4%BF%9D%E5%81%A5%E4%BF%A1%E6%81%AF%E4%B8%8E%E5%9C%A8%E7%BA%BF%E5%81%A5%E5%BA%B7%E6%9C%8D%E5%8A%A1%E5%B9%B3%E5%8F%B0&ari=2&ver=1221&dbv=2&drs=1&pcs=785x585&pss=1200x4673&cfv=0&cpl=0&chi=50&cce=true&cec=UTF-8&tlm=1673246196&prot=2&rw=600&ltu=http%3A%2F%2Fwww.39.net%2F&ecd=1&dft=0&uc=1920x1055&pis=-1x-1&sr=1920x1080&tcn=1673246196": 1,
      "https://pos.baidu.com/bcvm?di=u6055281&uuid=a107e2cf16a3e833&dri=0&dis=0&dai=3&ps=4673x0&enu=encoding&exps=110011&ant=0&psi=090d9c18b02ac805&dcb=___adblockplus_&dtm=SSP_JSONP&dvi=0.0&dci=-1&dpt=none&tpr=1673246195641&ti=39%E5%81%A5%E5%BA%B7%E7%BD%91_%E4%B8%AD%E5%9B%BD%E4%BC%98%E8%B4%A8%E5%8C%BB%E7%96%97%E4%BF%9D%E5%81%A5%E4%BF%A1%E6%81%AF%E4%B8%8E%E5%9C%A8%E7%BA%BF%E5%81%A5%E5%BA%B7%E6%9C%8D%E5%8A%A1%E5%B9%B3%E5%8F%B0&ari=2&ver=1221&dbv=2&drs=1&pcs=785x585&pss=1200x4673&cfv=0&cpl=0&chi=50&cce=true&cec=UTF-8&tlm=1673246196&prot=2&rw=600&ltu=http%3A%2F%2Fwww.39.net%2F&ecd=1&dft=0&uc=1920x1055&pis=-1x-1&sr=1920x1080&tcn=1673246196": 1,
      "https://pos.baidu.com/bcvm?conwid=600&conhei=90&rdid=6055282&dc=3&di=u6055282&s1=3252467561&s2=3207679011&dri=0&dis=0&dai=4&ps=4673x0&enu=encoding&exps=110277,110275,110261,110252,110011&ant=0&psi=090d9c18b02ac805&dcb=___adblockplus_&dtm=HTML_POST&dvi=0.0&dci=-1&dpt=none&tpr=1673246195641&ti=39%E5%81%A5%E5%BA%B7%E7%BD%91_%E4%B8%AD%E5%9B%BD%E4%BC%98%E8%B4%A8%E5%8C%BB%E7%96%97%E4%BF%9D%E5%81%A5%E4%BF%A1%E6%81%AF%E4%B8%8E%E5%9C%A8%E7%BA%BF%E5%81%A5%E5%BA%B7%E6%9C%8D%E5%8A%A1%E5%B9%B3%E5%8F%B0&ari=2&ver=1221&dbv=2&drs=1&pcs=785x585&pss=1200x4673&cfv=0&cpl=0&chi=50&cce=true&cec=UTF-8&tlm=1673246196&prot=2&rw=600&ltu=http%3A%2F%2Fwww.39.net%2F&ecd=1&dft=0&uc=1920x1055&pis=-1x-1&sr=1920x1080&tcn=1673246196&qn=0f8fa08d98ebf3ed&ft=1": 5,
      "https://pos.baidu.com/bcvm?conwid=600&conhei=90&rdid=6055281&dc=3&di=u6055281&s1=2701648591&s2=379840563&dri=0&dis=0&dai=3&ps=4673x0&enu=encoding&exps=110277,110275,110261,110252,110011&ant=0&psi=090d9c18b02ac805&dcb=___adblockplus_&dtm=HTML_POST&dvi=0.0&dci=-1&dpt=none&tpr=1673246195641&ti=39%E5%81%A5%E5%BA%B7%E7%BD%91_%E4%B8%AD%E5%9B%BD%E4%BC%98%E8%B4%A8%E5%8C%BB%E7%96%97%E4%BF%9D%E5%81%A5%E4%BF%A1%E6%81%AF%E4%B8%8E%E5%9C%A8%E7%BA%BF%E5%81%A5%E5%BA%B7%E6%9C%8D%E5%8A%A1%E5%B9%B3%E5%8F%B0&ari=2&ver=1221&dbv=2&drs=1&pcs=785x585&pss=1200x4673&cfv=0&cpl=0&chi=50&cce=true&cec=UTF-8&tlm=1673246196&prot=2&rw=600&ltu=http%3A%2F%2Fwww.39.net%2F&ecd=1&dft=0&uc=1920x1055&pis=-1x-1&sr=1920x1080&tcn=1673246196&qn=aa8326e615a0b8bd&ft=1": 5,
      "https://cpro.baidustatic.com/js/logo/js/logo.js": 12
    }
  },
  "2144.cn": {
    "rank": "923",
    "private": {
      "http://www.2144.cn/": 1,
      "https://www.2144.cn/": 2,
      "https://static.2144.cn/web/theme/site2016/topbar/js/topbar20200410.js": 12,
      "https://static.2144.cn/www/ptlogin20150901/js/webilr20190722.js": 18
    },
    "third": {
      "https://static.2144gy.com/www/n9/js/index.js": 40,
      "https://ssl.captcha.qq.com/TCaptcha.js": 7,
      "https://captcha.gtimg.com/1/tcaptcha-frame.54fe033f.js": 4
    }
  },
  "gjzq.com.cn": {
    "rank": "924",
    "private": {
      "https://www.gjzq.com.cn/main/index.html": 3,
      "https://www.gjzq.com.cn/static/main/js/libs/jquery.js": 6,
      "https://www.gjzq.com.cn/static/main/js/libs/plugins.js": 2,
      "https://www.gjzq.com.cn/static/main/js/app.js?v=20230109": 1
    },
    "third": {}
  },
  "locojoy.com": {
    "rank": "925",
    "private": {},
    "third": {}
  },
  "naver.jp": {
    "rank": "926",
    "private": {},
    "third": {}
  },
  "koolearn.com": {
    "rank": "927",
    "private": {
      "https://www.koolearn.com/": 4,
      "https://k12-pc.koocdn.com/js/index.1d977e9d.js": 20,
      "https://k12-pc.koocdn.com/js/chunk-common.65bdaff5.js": 1,
      "https://k12-pc.koocdn.com/js/chunk-vendors.69928eee.js": 11,
      "https://static.koocdn.com/project/xdf-analysis-log/1.x/js/page.bundle.js": 6
    },
    "third": {
      "https://assets.giocdn.com/2.1/gio.js": 33
    }
  },
  "hxnews.com": {
    "rank": "928",
    "private": {
      "http://www.hxnews.com/": 6
    },
    "third": {
      "https://hm.baidu.com/hm.js?0baf48bfc0469c5eb9b0ecac0610b290": 12
    }
  },
  "pornhubpremium.com": {
    "rank": "929",
    "private": {
      "https://www.pornhubpremium.com/": 2
    },
    "third": {
      "https://www.google-analytics.com/analytics.js": 18,
      "https://www.google-analytics.com/gtm/js?id=GTM-K9QH6V&cid=1965349531.1673246349": 5
    }
  },
  "cscec.com": {
    "rank": "930",
    "private": {
      "https://www.cscec.com/": 1
    },
    "third": {}
  },
  "500px.org": {
    "rank": "931",
    "private": {},
    "third": {
      "https://500px.com/": 21,
      "https://connect.facebook.net/en_US/fbevents.js": 17,
      "https://s.pinimg.com/ct/core.js": 4,
      "https://s.pinimg.com/ct/lib/main.9a94ee76.js": 20,
      "https://500px.com/staticV2/js/14.7cf34bbf.chunk.js": 677,
      "https://500px.com/staticV2/js/main.2d3b0930.chunk.js": 29,
      "https://www.googletagmanager.com/gtag/js?id=AW-10805689966": 16,
      "https://www.google-analytics.com/analytics.js": 14,
      "https://cdn4.buysellads.net/pub/500px.js?1673244000000": 8
    }
  },
  "dwstatic.com": {
    "rank": "932",
    "private": {},
    "third": {
      "https://cdn4.buysellads.net/pub/500px.js?1673244000000": 7,
      "https://c.amazon-adsystem.com/aax2/apstag.js": 24,
      "https://www.googletagservices.com/tag/js/gpt.js": 7
    }
  },
  "cutv.com": {
    "rank": "933",
    "private": {
      "http://www.cutv.com/": 4,
      "http://www.cutv.com/js/pc/jquery-1.11.1.min.js": 28,
      "http://www.cutv.com/js/pc/index.js?20200107": 9
    },
    "third": {}
  },
  "gcdn.co": {
    "rank": "934",
    "private": {},
    "third": {}
  },
  "mtime.cn": {
    "rank": "935",
    "private": {
      "http://www.mtime.cn/": 2,
      "http://s0.mtime.cn/public/nodewww/202212071445/js/common/common-index.js": 6,
      "http://s0.mtime.cn/public/nodewww/202212071445/js/index.js": 14
    },
    "third": {}
  },
  "17173cdn.com": {
    "rank": "936",
    "private": {},
    "third": {}
  },
  "billionconnect.com": {
    "rank": "937",
    "private": {
      "http://www.billionconnect.com/": 1
    },
    "third": {}
  },
  "pai-hang-bang.com": {
    "rank": "938",
    "private": {
      "http://www.pai-hang-bang.com/imgs/js/tj.js": 2
    },
    "third": {}
  },
  "zoossoft.net": {
    "rank": "939",
    "private": {
      "http://www.zoossoft.net/static/js/main.js": 2,
      "https://testserver.zoosnet.net/JS/LsJS.aspx?siteid=lza69557093&lng=cn": 11,
      "https://testserver.zoosnet.net//lr/ChatBW3JS.aspx?jid=d": 16,
      "https://testserver.zoosnet.net/LR/minichat_PC.aspx?id=LZA69557093&cid=3e8d55f6b0304c73ad401a7d19bde572&lng=cn&sid=3e8d55f6b0304c73ad401a7d19bde572&p=http%3A//www.zoossoft.net/&r=&msg=": 1
    },
    "third": {}
  },
  "520730.com": {
    "rank": "940",
    "private": {
      "https://www.520730.com/skin/blpc/js/uabl.js": 4
    },
    "third": {
      "https://testserver.zoosnet.net/JS/LsJS.aspx?siteid=lza69557093&lng=cn": 2,
      "https://testserver.zoosnet.net//lr/ChatBW3JS.aspx?jid=d": 3
    }
  },
  "caixin.com": {
    "rank": "941",
    "private": {
      "https://file.caixin.com/webchannel/home/js/all_v6.js": 1,
      "https://file.caixin.com/webjs/jquery-2.1.3.min.js": 18,
      "https://file.caixin.com/en/plugins/js/index.js": 9,
      "https://file.caixin.com/en/plugins/js/d3.min.js?_=1673246550158": 8
    },
    "third": {
      "https://www.caixinglobal.com/": 25,
      "https://connect.facebook.net/en_US/fbevents.js": 17,
      "https://pagead2.googlesyndication.com/pagead/js/adsbygoogle.js": 20,
      "https://www.googletagmanager.com/gtag/js?id=UA-86535477-1": 12,
      "https://www.google-analytics.com/analytics.js": 18,
      "https://cdn.taboola.com/libtrc/unip/1104137/tfa.js": 33,
      "https://assets.growingio.com/2.1/gio.js": 33,
      "https://pagead2.googlesyndication.com/pagead/managed/js/adsense/m202212010101/show_ads_impl.js": 83,
      "https://tpc.googlesyndication.com/sodar/sodar2.js": 61,
      "https://tpc.googlesyndication.com/sodar/sodar2/225/runner.html": 27
    }
  },
  "25pp.com": {
    "rank": "942",
    "private": {
      "https://www.25pp.com/": 6,
      "https://g.alicdn.com/alilog/mlog/aplus_v2.js": 17,
      "https://g.alicdn.com/secdev/entry/index.js?t=232395": 6,
      "https://g.alicdn.com/xlly/spl/rp.js": 2,
      "https://g.alicdn.com/sd/baxia-entry/index.js?t=232395": 4
    },
    "third": {}
  },
  "gnvip.net": {
    "rank": "943",
    "private": {
      "https://abtest.bangwo8.com/osp2016/im/js/chatInit_v3.js?bangwo8Info=OTgwMTE4YTY3ZjA5NjgwOTQxNWNhMWM5ZjExMmQ5NmQyNzY4OWI=": 8,
      "https://abtest.bangwo8.com/osp2016/im/js/sea-modules/jquery/jquery/1.10.1/jquery.js": 28,
      "https://abtest.bangwo8.com/osp2016/im/js/sea-modules/bw8im/im.entrance.js": 9,
      "https://abtest.bangwo8.com/osp2016/im/js/sea-modules/bw8im/im.behavior.js": 1,
      "https://abtest.bangwo8.com/osp2016/im/js/sea-modules/jquery/jquery/1.10.1/jquery.js?v=bg23fe0": 2,
      "https://abtest.bangwo8.com/osp2016/im/js/sea-modules/bw8im/im.trigger.js?v=bw822Newwcx90": 2,
      "https://abtest.bangwo8.com/osp2016/im/js/sea-modules/bw8im/im.robot.js?v=bw822Newwcx90": 2,
      "https://abtest.bangwo8.com/osp2016/im/js/sea-modules/bw8im/im.trigger.js": 2
    },
    "third": {
      "https://abtest.bangwo8.com/osp2016/im/js/sea-modules/seajs/sea.js?rs=std-20230": 66,
      "https://abtest.bangwo8.com/osp2016/im/js/sea-modules/seajs/sea.js?v=a8aec5d6": 97,
      "https://abtest.bangwo8.com/osp2016/im/pc/index.php?vendorID=18&uid=u2_18_914123278251&customInfo=&tagName=%CD%E2%B2%BF&adID=0&cateList=11700,7329,7093,6859,6857,6065,6063,4245,674,567,443,441,439&display_remote=&skinId=155&signature_skip=1&robot=1&origin_account=&bw8_lang=undefined&customClientInfo=undefined&customSource=gnway.com&displayMin=1": 1,
      "https://abtest.bangwo8.com/osp2016/im/js/sea-modules/bw8im/im.pc.main.js?v=bw822Newwcx90": 2
    }
  },
  "battleofballs.com": {
    "rank": "944",
    "private": {
      "http://www.battleofballs.com/": 2,
      "https://www.battleofballs.com/index_PC.html": 6
    },
    "third": {}
  },
  "118100.cn": {
    "rank": "945",
    "private": {},
    "third": {
      "https://gaanalytics.ztgame.com/analytics.js?1673246862602": 2,
      "https://www.imusic.cn/": 2,
      "https://www.imusic.cn/static/js/vendor.fae935b07c4f638e1d3f.js": 6,
      "https://ty-apm.imusic.cn/js/4Nl_NnGbjwY.js": 15
    }
  },
  "nuskin.com": {
    "rank": "946",
    "private": {
      "https://www.nuskin.com/nuskin.html": 2
    },
    "third": {
      "https://ty-apm.imusic.cn/js/4Nl_NnGbjwY.js": 19,
      "https://unpkg.com/axios@1.0.0/dist/axios.min.js": 12
    }
  },
  "pokemon.com": {
    "rank": "947",
    "private": {
      "https://www.pokemon.com/": 2,
      "https://www.pokemon.com/us": 2,
      "https://assets.pokemon.com/static2/_ui/js/vendor/require.js": 36,
      "https://assets.pokemon.com/static2/_ui/js/main.js": 28
    },
    "third": {
      "https://ajax.googleapis.com/ajax/libs/jquery/3.6.1/jquery.min.js": 8,
      "https://www.nuskin.com/apps/hello/layouts/global_redirect_whitepage/clientlib.js": 7,
      "https://www.nuskin.com/nuskin.html": 3,
      "https://www.googletagmanager.com/gtm.js?id=GTM-V9L7": 22,
      "https://cdn.cookielaw.org/scripttemplates/otSDKStub.js": 14,
      "https://cdn.cookielaw.org/scripttemplates/6.33.0/otBannerSdk.js": 81,
      "webpack:///./src/gus.js?": 4
    }
  },
  "9duw.com": {
    "rank": "948",
    "private": {},
    "third": {
      "https://cdn.cookielaw.org/scripttemplates/6.33.0/otBannerSdk.js": 2
    }
  },
  "dmzj.com": {
    "rank": "949",
    "private": {
      "https://www.dmzj.com/js/ad/ad_15.js?v=1": 1,
      "https://www.dmzj.com/js/ad/ad_22.js?v=1": 1,
      "https://www.dmzj.com/": 5,
      "https://static.dmzj.com/public/js/jquery-1.8.2.min.js": 12,
      "https://static.dmzj.com/public/js/app_banner.js": 1,
      "https://static.dmzj.com/public/js/loadscript.js": 3,
      "https://static.dmzj.com/public/js/dmzj-land-2015.6.dmzj1.js?20156030?time=1673246912000": 2
    },
    "third": {
      "https://pc.stgowan.com/pc/couplet-tf.js": 3,
      "https://www.googletagmanager.com/gtag/js?id=G-JEZCSW6TY5": 19,
      "https://pc.stgowan.com/pc_w/m_couplet.js": 1
    }
  },
  "kingroot.net": {
    "rank": "950",
    "private": {},
    "third": {}
  },
  "bulgari.com": {
    "rank": "951",
    "private": {},
    "third": {}
  },
  "pa18.com": {
    "rank": "952",
    "private": {
      "https://script2.pingan.com/app_js/pingan/libs/browser.js": 10,
      "https://script2.pingan.com/app_js/pingan/libs/paui/pa.ui.min.js": 16,
      "https://script2.pingan.com/app_js/pingan/libs/paui/city.js": 8,
      "https://www.pingan.com/official/page/index-type/index-d03cf3ff77.js": 110,
      "https://script2.pingan.com/app_series/statistic/gwPAReport.min.js": 4,
      "https://iobs02.pingan.com.cn/download/eits-access-dmz-prd/PAD_H5_SDK_3.1.8_vr1.js": 8
    },
    "third": {}
  },
  "changhong.com": {
    "rank": "953",
    "private": {
      "https://cn.changhong.com/images/jquery.min.js": 55,
      "https://cn.changhong.com/": 14,
      "https://images.changhong.com/chgw/images/tingyun.js": 23,
      "https://cn.changhong.com/mobile/images/onlineConsultation.js": 1,
      "https://cn.changhong.com/images/changhong_common.js": 2,
      "https://cn.changhong.com/images/cartCookie.js": 2,
      "https://cn.changhong.com/images/getdata.js": 2,
      "https://images.changhong.com/chgw/images/im.js": 2
    },
    "third": {
      "https://s4.cnzz.com/z_stat.php?id=1258600689&web_id=1258600689": 4,
      "https://assets-cli.s4.udesk.cn/im_client/js/udeskApi.js": 9,
      "https://1871785.s4.udesk.cn/spa1/im_web_plugins/32991/out_config?company_code=1ccj2i3d&language=&session_key=&callback=udesk_jsonp0": 1
    }
  },
  "newmotor.com.cn": {
    "rank": "954",
    "private": {},
    "third": {}
  },
  "llnwi.net": {
    "rank": "955",
    "private": {},
    "third": {
      "http://www.newmotor.com.cn/": 1,
      "https://cbjs.baidu.com/js/m.js": 64,
      "https://www.newmotor.com.cn/": 16,
      "https://www.newmotor.com.cn/js/201412newindex/1.7.2.min.js": 4,
      "https://www.newmotor.com.cn/ks_inc/jquery-1.9.1.min.js": 4,
      "https://sofire.bdstatic.com/js/dfxaf3-635b4cd6.js": 9
    }
  },
  "hillstonenet.com": {
    "rank": "956",
    "private": {
      "https://www.hillstonenet.com/": 7
    },
    "third": {
      "https://js.hsforms.net/forms/v2.js": 15,
      "https://js.hs-scripts.com/9151864.js": 8,
      "https://www.googletagmanager.com/gtm.js?id=GTM-PCWC3SQ": 40,
      "https://d10lpsik1i8c69.cloudfront.net/w.js": 12,
      "https://www.google-analytics.com/analytics.js": 18,
      "https://js.hscollectedforms.net/collectedforms.js": 3,
      "https://js.hsadspixel.net/fb.js": 22,
      "https://js.hs-banner.com/v2/9151864/banner.js": 10,
      "https://snap.licdn.com/li.lms-analytics/insight.min.js": 2,
      "https://snap.licdn.com/li.lms-analytics/insight.old.min.js": 25,
      "https://d10lpsik1i8c69.cloudfront.net/js/clickstream.js?v=e708588": 66,
      "https://www.googletagmanager.com/gtag/js?id=AW-948829196": 16,
      "https://connect.facebook.net/en_US/fbevents.js": 33
    }
  },
  "yesky.com": {
    "rank": "957",
    "private": {
      "http://www.yesky.com/": 19
    },
    "third": {
      "https://connect.facebook.net/en_US/fbevents.js": 5,
      "https://connect.facebook.net/signals/config/879493855960708?v=2.9.91&r=stable": 2,
      "https://pagead2.googlesyndication.com/pagead/js/adsbygoogle.js?client=ca-pub-9647159939428271": 20,
      "https://pagead2.googlesyndication.com/pagead/managed/js/adsense/m202212080101/show_ads_impl.js?bust=31071277": 78,
      "https://tpc.googlesyndication.com/sodar/sodar2.js": 61,
      "https://tpc.googlesyndication.com/sodar/sodar2/225/runner.html": 27
    }
  },
  "paojiao.cn": {
    "rank": "958",
    "private": {
      "https://www.paojiao.cn/js/jq.js?v=eee": 2
    },
    "third": {}
  },
  "vidible.tv": {
    "rank": "959",
    "private": {},
    "third": {}
  },
  "kuwo.cn": {
    "rank": "960",
    "private": {
      "https://h5static.kuwo.cn/www/kw-www/app.0103313.js": 35,
      "https://h5static.kuwo.cn/www/kw-www/runtime.8dab5cd.js": 23,
      "https://h5static.kuwo.cn/www/kw-www/vendors/commons.a320f06.js": 6
    },
    "third": {
      "https://www.google-analytics.com/analytics.js": 18,
      "https://hm.baidu.com/hm.js?cdb524f42f0ce19b169a8071123a4797": 12
    }
  },
  "ey.com": {
    "rank": "961",
    "private": {
      "https://assets.ey.com/etc/designs/zg/eydff/desktop/js.asset.js/core/design.default.bootstrap.v.js": 282
    },
    "third": {
      "https://assets.adobedtm.com/launch-EN7b2377b853464a1ea1e51ee3defd088a.min.js": 53,
      "https://public.flourish.studio/resources/embed.js": 4,
      "https://flo.uri.sh/visualisation/7671763/embed?auto=1": 21
    }
  },
  "zlongame.com": {
    "rank": "962",
    "private": {
      "https://www.zlongame.com/common/unit/public/1.0.0/public.js": 20,
      "https://media.zlongame.com/media/common/vendor/jquery/1.11.3/jquery.js": 23,
      "https://www.zlongame.com/html/js/index.js": 5
    },
    "third": {}
  },
  "feidee.com": {
    "rank": "963",
    "private": {
      "http://www.feidee.com/money/": 6,
      "https://www.feidee.com/money/js/plugin/jquery.min-3gmin.js?86135": 2,
      "https://www.feidee.com/money/js/index/activity-3gmin.js?649": 1,
      "https://www.feidee.com/money/js/index/welcome-3gmin.js?4109": 2,
      "https://resources.sui.com/fed/analytics/__spm.js?v=9": 4
    },
    "third": {}
  },
  "sdtele.com": {
    "rank": "964",
    "private": {},
    "third": {}
  },
  "weixinbridge.com": {
    "rank": "965",
    "private": {},
    "third": {}
  },
  "tietuku.cn": {
    "rank": "966",
    "private": {
      "http://www.tietuku.cn/static/js/index.ef2f0d.js": 8,
      "http://www.tietuku.cn/static/js/base.js": 7
    },
    "third": {}
  },
  "focus.cn": {
    "rank": "967",
    "private": {
      "https://zjj.focus.cn/?useIp=true": 2
    },
    "third": {
      "https://assets.growingio.com/2.1/gio.js": 38,
      "https://t.focus-res.cn/front-end/stat.js": 8,
      "https://t.focus-res.cn/front-pc/next/city-new/city-new.5475a33c38d8011c5d7b.js": 140,
      "https://t.focus-res.cn/front-pc/next/manifest/manifest.7fc0c6c7518c07bc7441.js": 40,
      "https://t.focus-res.cn/front-pc/next/bundle/bundle.dbff5e998e9900dff86e.js": 26,
      "https://t1.focus-res.cn/seo-sv/header-footer/assets/header/header.2a912c46766727d96998.js": 27,
      "https://t.focus-res.cn/front-end/ecology/adLog.min.js": 7,
      "https://t.focus-res.cn/front-end/ecology/pc-im/im-new.js": 15,
      "https://t.focus-res.cn/front-end/ecology/newlogin.min.js": 32,
      "https://t.focus-res.cn/front-end/red-packet/js/dsp-new.min.js": 6
    }
  },
  "jaeapp.com": {
    "rank": "968",
    "private": {},
    "third": {
      "https://assets.growingio.com/2.1/gio.js": 10,
      "https://t.focus-res.cn/front-end/ecology/adLog.min.js": 3,
      "https://t.focus-res.cn/front-pc/next/city-new/city-new.5475a33c38d8011c5d7b.js": 2
    }
  },
  "qiku.com": {
    "rank": "969",
    "private": {
      "http://www.qiku.com/": 4
    },
    "third": {
      "https://www.google-analytics.com/analytics.js": 13
    }
  },
  "hynews.net": {
    "rank": "970",
    "private": {},
    "third": {
      "https://news.ha101.cn/common/common.js": 11,
      "https://news.ha101.cn/common/m.index.js": 1,
      "https://news.ha101.cn/common/jquery-3.3.1.min.js": 2,
      "https://news.ha101.cn/common/analytics.js": 2,
      "https://news.ha101.cn/common/jquery-2.2.4.min.js": 4,
      "https://news.ha101.cn/common/pc.menu.js": 2,
      "https://news.ha101.cn/common/pc.index.js": 2
    }
  },
  "vhall.com": {
    "rank": "971",
    "private": {
      "https://www.vhall.com/": 8,
      "https://www.vhall.com/public/js/sa-sdk-javascript@1.16.6/sensorsdata.min.js": 53,
      "https://www.vhall.com/public/js/abtest.min.js": 23
    },
    "third": {
      "https://news.ha101.cn/common/jquery-2.2.4.min.js": 37,
      "https://news.ha101.cn/common/common.js": 12,
      "https://news.ha101.cn/common/pc.menu.js": 13,
      "https://news.ha101.cn/common/pc.index.js": 1,
      "https://assets-cli.udesk.cn/im_client/js/udeskApi.js": 185,
      "https://vhall.s4.udesk.cn/spa1/im_web_plugins/15038/out_config?company_code=fk7hebc&language=&session_key=&callback=udesk_jsonp0": 2,
      "https://basevistor.s4.udesk.cn/customerApi/key?_=&is_invite=1&code=fk7hebc&url=https%3A%2F%2Fwww.vhall.com%2F&referrer=&keyword=&title=%E5%BE%AE%E5%90%BC-%E4%BC%81%E4%B8%9A%E7%9B%B4%E6%92%AD%E5%B9%B3%E5%8F%B0%E4%B8%8E%E8%BF%90%E8%90%A5%E6%9C%8D%E5%8A%A1%E5%95%86%2C%E8%90%A5%E9%94%80%E3%80%81%E4%BC%9A%E8%AE%AE%E3%80%81%E5%9F%B9%E8%AE%AD%E7%9B%B4%E6%92%AD-%E5%BE%AE%E5%90%BC%E6%97%B6%E4%BB%A3&scaleScreen=1920*1080&callback=udesk_jsonp1": 2,
      "https://vhall.s4.udesk.cn/agents/free?im_web_plugin_id=15038&session_key=&callback=udesk_jsonp2": 1,
      "https://vhall.s4.udesk.cn/im_client/My97DatePicker/WdatePicker.js": 3,
      "https://static-ud.udesk.cn/lib/jquery/1.11.3/jquery.min.js": 13,
      "https://static-ud.s4.udesk.cn/im_client/main.a1eb95d0.js": 8
    }
  },
  "worldofwarcraft.com": {
    "rank": "972",
    "private": {
      "https://worldofwarcraft.com/en-us/": 126,
      "https://assets.worldofwarcraft.com/static/runtime.3184bdf742ce22e09a41.js": 16,
      "https://assets.worldofwarcraft.com/static/3.e30d66be3249cee6c3f3.js": 9,
      "https://assets.worldofwarcraft.com/static/legacy-components.3ca86fc74c3b671e9b4d.js": 6,
      "https://assets.worldofwarcraft.com/static/scripts/cookie-consent.min.js?v=8.46.2": 60,
      "https://assets.worldofwarcraft.com/static/masthead-featured-news-mount.7e23100044fa71610172.js": 6,
      "https://assets.worldofwarcraft.com/static/vendor.031aaa029db57c33626f.js": 16,
      "https://assets.worldofwarcraft.com/static/core.edc1f70fb256bace5f8c.js": 3
    },
    "third": {
      "https://www.googletagmanager.com/gtm.js?id=GTM-5BZVX9": 320,
      "https://geo.battle.net/onetrust-banner": 15,
      "https://connect.facebook.net/en_US/fbevents.js": 22,
      "https://navbar.blizzard.com/static/v1/footer.js": 6,
      "https://www.youtube.com/iframe_api": 2,
      "https://bat.bing.com/bat.js": 4,
      "https://www.google-analytics.com/analytics.js": 70,
      "https://blznav.akamaized.net/public/gacrossdomain.html": 4,
      "https://sc-static.net/scevent.min.js": 97,
      "https://snap.licdn.com/li.lms-analytics/insight.min.js": 2,
      "https://snap.licdn.com/li.lms-analytics/insight.old.min.js": 25,
      "https://cdn.optimizely.com/js/8520856750.js": 15,
      "https://analytics.tiktok.com/i18n/pixel/events.js?sdkid=CBVCBGBC77UFTR6U5U4G&lib=ttq": 2,
      "https://connect.facebook.net/signals/config/1909472906008824?v=2.9.91&r=stable": 2,
      "https://analytics.tiktok.com/i18n/pixel/static/main.MWI1MTgwZGZmNQ.js": 221,
      "https://tr.snapchat.com/cm/i?pid=9b207acc-0e29-4f90-bb3d-e173ed766e12&u_scsid=49d7c43c-bc05-49ca-8835-004cde1d2db0&u_sclid=a49760bd-ecfb-460b-9287-1b97622e1066": 2,
      "https://tr.snapchat.com/cm/i?pid=ad7cb8f0-30df-4c2a-87b3-f44e3c6c27b0&u_scsid=49d7c43c-bc05-49ca-8835-004cde1d2db0&u_sclid=a49760bd-ecfb-460b-9287-1b97622e1066": 2,
      "https://js-agent.newrelic.com/nr-spa-1184.min.js": 7
    }
  },
  "daily.co.uk": {
    "rank": "973",
    "private": {},
    "third": {
      "https://worldofwarcraft.com/en-us/": 2,
      "https://js-agent.newrelic.com/nr-spa-1184.min.js": 6
    }
  },
  "kii.com": {
    "rank": "974",
    "private": {
      "https://en.kii.com/": 5
    },
    "third": {
      "https://www.google.com/recaptcha/api.js": 2,
      "https://www.google-analytics.com/analytics.js": 13,
      "https://www.gstatic.com/recaptcha/releases/5qcenVbrhOy8zihcc2aHOWD4/recaptcha__en.js": 16
    }
  },
  "biligame.com": {
    "rank": "975",
    "private": {},
    "third": {
      "http://s1.hdslb.com/bfs/seed/game-web/duang/header/header.js": 9,
      "http://s1.hdslb.com/bfs/static/game-web/duang/home/1.home.1febc3c76c17ff84d43b4c84cb7b55faf8e8affd.js": 38,
      "http://s1.hdslb.com/bfs/static/game-web/duang/home/home.1febc3c76c17ff84d43b4c84cb7b55faf8e8affd.js": 11,
      "http://s1.hdslb.com/bfs/static/jinkela/long/js/sentry/sentry-5.7.1.min.js": 16,
      "http://s1.hdslb.com/bfs/seed/log/report/log-reporter.js": 108
    }
  },
  "xiangha.com": {
    "rank": "976",
    "private": {
      "https://www.xiangha.com/": 4,
      "https://khrtac.xiangha.com/common/res/v3nlv.js?lg=ppdyohh": 16,
      "https://khrtac.xiangha.com/xtvzuvo.js": 19
    },
    "third": {
      "http://s1.hdslb.com/bfs/seed/log/report/log-reporter.js": 12,
      "http://s1.hdslb.com/bfs/static/jinkela/long/js/sentry/sentry-5.7.1.min.js": 2,
      "https://s2.cdn.jiaonizuocai.com/js/bootcss/bootcss_171_jquery.min.js": 2,
      "https://s2.cdn.jiaonizuocai.com/js/m4/stat.js?vs=20221222175524": 1,
      "https://retcode.alicdn.com/retcode/bl.js": 51,
      "https://sofire.bdstatic.com/js/dfxaf3-635b4cd6.js": 9
    }
  },
  "haodf.com": {
    "rank": "977",
    "private": {
      "https://i2.hdfimg.com/js/seagullbegin.js": 8,
      "https://i2.hdfimg.com/ssi/usercenter/js/hdf_login.js?time=202105181042": 3,
      "https://www.haodf.com/": 2,
      "https://i2.hdfimg.com/js/seagullend.js?2023019": 14,
      "https://i2.hdfimg.com/js/jquery-1.4.2.min.js": 12,
      "https://i2.hdfimg.com/js/fancybox/fancybox.js?1358357449": 2,
      "https://i2.hdfimg.com/js/jquery-1.4.2.min.js?20101126": 5,
      "https://i2.hdfimg.com/www/js/twodimension.js?20140916": 1
    },
    "third": {
      "https://retcode.alicdn.com/retcode/bl.js": 13,
      "https://fe1.hdfimg.com/nmenzhen/pcguahao/script/pcindex/index.ef7f7654.js": 33,
      "https://i2.hdfimg.com/js/pvstat.js?20151209": 2
    }
  },
  "letfap.com": {
    "rank": "978",
    "private": {
      "https://xart.letfap.com/": 8,
      "https://statics.letfap.com/assets/love/index.js?_=20190719": 2,
      "https://statics.letfap.com/assets/js/jquery.min.js": 10,
      "https://statics.letfap.com/assets/js/app.min.js?_=20190719": 2,
      "https://statics.letfap.com/assets/js/ejs.min.js": 2
    },
    "third": {
      "https://i2.hdfimg.com/js/seagullend.js?2023019": 9,
      "https://www.google-analytics.com/analytics.js": 13,
      "https://syndication.exoclick.com/splash.php?idzone=1792064&type=12&capping=0": 4,
      "https://syndication.exoclick.com/splash.php?idzone=1792058&type=4": 10,
      "https://creative.xlivrdr.com/widgets/v4/Universal/main.ca42ccb072e99a5a6126.js": 853
    }
  },
  "ovivowater.com": {
    "rank": "979",
    "private": {
      "https://www.ovivowater.com/en/": 5
    },
    "third": {
      "https://www.googletagmanager.com/gtag/js?id=UA-18781550-1": 17,
      "https://www.google-analytics.com/analytics.js": 13,
      "https://www.googletagmanager.com/gtm.js?id=GTM-PT5HBDQ": 88,
      "https://bat.bing.com/bat.js": 3,
      "https://www.googletagmanager.com/gtag/js?id=G-3N3F1TJNT7&l=dataLayer&cx=c": 46,
      "https://acsbapp.com/apps/app/dist/js/app.js": 11,
      "https://cdn.calltrk.com/companies/205035836/d625593f098d4d02b587/12/swap.js": 17
    }
  },
  "bethesda.net": {
    "rank": "980",
    "private": {
      "https://bethesda.net/_static-bwa/index.58b7ec11.js": 279
    },
    "third": {
      "https://www.google-analytics.com/analytics.js": 18,
      "https://cdn.cookielaw.org/scripttemplates/otSDKStub.js": 6
    }
  },
  "ksmobile.net": {
    "rank": "981",
    "private": {},
    "third": {
      "https://cdn.cookielaw.org/scripttemplates/otSDKStub.js": 4
    }
  },
  "freeriderhd.com": {
    "rank": "982",
    "private": {
      "https://www.freeriderhd.com/": 7,
      "https://cdn.freeriderhd.com/free_rider_hd/scripts/shared/frhd_shared.min.149.1203950067.js": 28,
      "https://cdn.freeriderhd.com/free_rider_hd/assets/scripts/gamemanager/game_manager.min.26.0.58.55.js": 276,
      "https://cdn.freeriderhd.com/free_rider_hd/scripts/application/frhd_app.min.514.1694970797.js": 11
    },
    "third": {
      "https://www.googletagservices.com/tag/js/gpt.js": 7,
      "https://www.google-analytics.com/analytics.js": 13,
      "https://connect.facebook.net/en_US/sdk.js": 2,
      "https://connect.facebook.net/en_US/sdk.js?hash=2977d64b19ca9b033da9b0b73728a1d2": 14,
      "https://securepubads.g.doubleclick.net/gpt/pubads_impl_2022120801.js": 59,
      "https://tpc.googlesyndication.com/sodar/sodar2.js": 61,
      "https://tpc.googlesyndication.com/sodar/sodar2/225/runner.html": 27
    }
  },
  "dailyinnovation.biz": {
    "rank": "983",
    "private": {},
    "third": {}
  },
  "bitauto.com": {
    "rank": "984",
    "private": {
      "https://d2.yiche.com/js/senseNew.js": 11,
      "https://www.yiche.com/": 7,
      "https://static1.bitautoimg.com/web-component/yiche-utils-pm/index-V259.min.js": 36,
      "https://img1.bitautoimg.com/web-component/yiche-search-pc/index-V118.min.js": 1,
      "https://static1.bitautoimg.com/yc-pc/index-pc/js/home-f0c7454ff1.js": 37,
      "https://static1.bitautoimg.com/uimg/2016/yiche/js/jquery-1.11.3.min.js": 52,
      "https://img.easypass.cn/das/cheyingtong/cyt.js": 5,
      "https://ga.yiche.com/autolog": 4,
      "https://static1.bitautoimg.com/web-component/components-axios/index-V100.min.js": 3,
      "https://static1.bitautoimg.com/web-component/yiche-city-pc/index-V139.min.js": 10
    },
    "third": {}
  },
  "findoout.com": {
    "rank": "985",
    "private": {
      "http://www.findoout.com/": 2,
      "http://www.findoout.com/statics/js/com/jquery.js": 17,
      "http://www.findoout.com/statics/js/src/findoout/index/main.min.js": 2
    },
    "third": {
      "https://static1.bitautoimg.com/web-component/yiche-utils-pm/index-V259.min.js": 4,
      "https://ga.yiche.com/autolog": 2
    }
  },
  "aliyun.com": {
    "rank": "986",
    "private": {
      "https://www.aliyun.com/": 4,
      "https://retcode.alicdn.com/retcode/bl.js": 707,
      "https://g.alicdn.com/alilog/mlog/aplus_v2.js": 28,
      "https://g.alicdn.com/??homon/page-render/3.1.10/v1/index.js": 2227,
      "https://g.alicdn.com/??dawn/user-tracker/2.0.59/js/index.js": 57,
      "https://g.alicdn.com/??dawn/polyfill/2.0.0/js/index.js,dawn/ace-static/0.0.2/react.js,dawn/ace-static/0.0.2/react-dom.js,aliyun/util/1.2.30/index.js,dawn/ace-element/0.0.60/index.js": 339,
      "https://g.alicdn.com/hmod/ace-2021-yunxiaobao-guide/0.0.10/??index.js,services.js": 9,
      "https://cloud-assets.alicdn.com/website.js": 11,
      "https://g.alicdn.com/dawn/smarter-engine/1.0.3/js/index.js": 27,
      "https://www.aliyun.com/smarter-engine": 2,
      "https://g.alicdn.com/aliyun/util/1.2.94/module/Account.js": 3,
      "https://g.alicdn.com/hmod/ace-homepage-2020-banner/0.0.167/??index.js,services.js": 18,
      "https://g.alicdn.com/secdev/entry/index.js?t=232395": 18,
      "https://g.alicdn.com/secdev/sufei_data/3.9.10/index.js": 63,
      "https://g.alicdn.com/hmod/ace-homepage-2020-topbar/0.0.702/??index.js,services.js": 16,
      "https://g.alicdn.com/aliyun/util/1.2.99/module/Delivery.js": 57,
      "https://g.alicdn.com/sd/baxia-entry/index.js?t=232395": 8,
      "https://g.alicdn.com/hmod/ace-homepage-2020-solution/0.0.25/??index.js,services.js": 24,
      "https://g.alicdn.com/hmod/ace-main-secondary-tab/0.0.21/??index.js,services.js": 33,
      "https://g.alicdn.com/sd/baxia/2.2.3/baxiaCommon.js": 55,
      "https://g.alicdn.com/aliyun/util/1.2.98/module/DataManager.js": 38,
      "https://g.alicdn.com/aliyun/util/1.2.57/module/Content.js": 39,
      "https://g.alicdn.com/hmod/ace-homepage-2020-talk/0.0.5/??index.js,services.js": 6,
      "https://g.alicdn.com/BigDipper/Dubhe/0.0.20/js/client.js": 16,
      "https://g.alicdn.com/??xlly/spl/rp.js,secdev/nsv/1.0.87/ns_f_95_3_f.js?v=1": 45,
      "https://g.alicdn.com/AWSC/et/1.62.7/et_f.js": 45,
      "https://g.alicdn.com/hmod/ace-merak-simplify-card/0.0.33/??index.js,services.js": 16,
      "https://g.alicdn.com/BigDipper/goods-service/0.0.8/index.js": 186,
      "https://g.alicdn.com/alilog/s/8.15.21/plugin/aplus_ae.js": 14,
      "https://g.alicdn.com/alilog/aplus_plugin_xwj/index.js?t=232395": 2
    },
    "third": {}
  },
  "wicp.net": {
    "rank": "987",
    "private": {},
    "third": {
      "https://retcode.alicdn.com/retcode/bl.js": 13
    }
  },
  "kuaidihelp.com": {
    "rank": "988",
    "private": {
      "https://www.kuaidihelp.com/": 8,
      "https://cdn-js.kuaidihelp.com/m.v3.0/jquery-3.1.0.min.js": 14,
      "https://cdn-css.kuaidihelp.com/m/layui/layui.js": 1
    },
    "third": {
      "https://d.alicdn.com/alilog/mlog/aplus/203467608.js": 49,
      "https://wuchaolong.github.io/baiduShare/static/api/js/share.js?v=89860593.js?": 143,
      "https://wuchaolong.github.io/baiduShare/static/api/js/view/select_view.js?v=85fc7cec.js": 2,
      "https://wuchaolong.github.io/baiduShare/static/api/js/share/slide_api.js?v=ec14f516.js": 2,
      "https://wuchaolong.github.io/baiduShare/static/api/js/view/slide_view.js?v=08373964.js": 2,
      "https://wuchaolong.github.io/baiduShare/static/api/js/share/api_base.js": 1,
      "https://wuchaolong.github.io/baiduShare/static/api/js/base/tangram.js?v=37768233.js": 1
    }
  },
  "tuling123.com": {
    "rank": "989",
    "private": {},
    "third": {
      "http://www.turingapi.com/": 2,
      "http://assets.growingio.com/2.1/gio.js": 23,
      "http://www.turingapi.com/static/js/manifest.3ecda23d0ba8aa4fe73c.js": 15,
      "http://www.turingapi.com/static/js/app.08ca47bf375ea261a6b4.js": 19,
      "http://www.turingapi.com/static/js/vendor.c27322d05c4bc8793f6b.js": 83
    }
  },
  "upcdn.net": {
    "rank": "990",
    "private": {},
    "third": {}
  },
  "upaiyun.com": {
    "rank": "991",
    "private": {},
    "third": {}
  },
  "pinshan.com": {
    "rank": "992",
    "private": {
      "https://www.pinshan.com/": 1
    },
    "third": {}
  },
  "taopiaopiao.com": {
    "rank": "993",
    "private": {
      "https://www.taopiaopiao.com/": 4
    },
    "third": {
      "https://uaction.alicdn.com/js/uab.js": 6,
      "https://g.alicdn.com/??kissy/k/1.4.16/seed-min.js,kg/kmd-adapter/0.1.5/index.js,kg/kmd-adapter/0.1.5/util.js,kg/global-util/1.0.7/index-min.js,tb/tracker/index.js": 561,
      "https://g.alicdn.com/alilog/mlog/aplus_v2.js": 17,
      "https://o.alicdn.com/tbhome/tbnav/index.js": 7,
      "https://g.alicdn.com/kissy/k/1.4.16/io-min.js": 11,
      "https://g.alicdn.com/life/pc-movie/1.0.44/pages/header/index.js": 4,
      "https://g.alicdn.com/sd/baxia-entry/index.js?t=232395": 4,
      "https://g.alicdn.com/secdev/entry/index.js?t=232395": 9,
      "https://g.alicdn.com/??xlly/spl/rp.js,secdev/nsv/1.0.87/ns_f_95_3_f.js?v=1": 3,
      "https://g.alicdn.com/life/pc-movie/1.0.44/pages/home/index.js": 6,
      "https://g.alicdn.com/sd/baxia/2.2.3/baxiaCommon.js": 1,
      "https://g.alicdn.com/secdev/sufei_data/3.9.10/index.js": 1,
      "https://g.alicdn.com/AWSC/et/1.62.7/et_f.js": 1
    }
  },
  "kdslife.com": {
    "rank": "994",
    "private": {
      "https://www.kdslife.com/": 4,
      "https://static.kdslife.com/public/framework/jquery/jquery-1.7.2.min.js": 4
    },
    "third": {
      "https://static.mediav.com/js/feed_ts.js": 6,
      "https://pagead2.googlesyndication.com/pagead/js/adsbygoogle.js?client=ca-pub-2322073735065674": 20,
      "https://pagead2.googlesyndication.com/pagead/managed/js/adsense/m202212050104/show_ads_impl.js?bust=31071387": 83,
      "https://tpc.googlesyndication.com/sodar/sodar2.js": 61,
      "https://tpc.googlesyndication.com/sodar/sodar2/225/runner.html": 27
    }
  },
  "zhijinwang.com": {
    "rank": "995",
    "private": {
      "http://www.zhijinwang.com/": 1
    },
    "third": {
      "http://cbjs.baidu.com/js/o.js": 59,
      "http://sofire.bdstatic.com/js/dfxaf3-635b4cd6.js": 46,
      "https://pos.baidu.com/wckm?di=353027&uuid=5e1b5e8d5e00944a&dri=0&dis=0&dai=0&ps=1521x1&enu=encoding&exps=110011&ant=0&psi=88a50d752a018ab6&dcb=___adblockplus_&dtm=SSP_JSONP&dvi=0.0&dci=-1&dpt=none&tpr=1673247993475&ti=%E7%BA%B8%E9%87%91%E7%BD%91%20-%20%E7%BA%B8%E9%BB%84%E9%87%91_%E9%BB%84%E9%87%91%E4%BB%B7%E6%A0%BC_%E9%BB%84%E9%87%91%E8%B5%B0%E5%8A%BF%E5%9B%BE%E5%92%8C%E9%BB%84%E9%87%91%E8%B5%84%E8%AE%AF%E6%9F%A5%E8%AF%A2%E5%B9%B3%E5%8F%B0&ari=2&ver=1221&dbv=2&drs=1&pcs=785x585&pss=1000x1522&cfv=0&cpl=0&chi=50&cce=true&cec=GBK&tlm=1673233220&prot=2&rw=600&ltu=http%3A%2F%2Fwww.zhijinwang.com%2F&ecd=1&fpt=UAoFTCMVudOeSrFRCIQ0Qwf8DcNKHJq1oUrzNMvtAwOj5xGDCoNZQMbT1vFzIP93RWSWpf9gqdWihxlI3+MyVBopLjJnAHXg8WPlGy+5NKKf2wwWrr5i0CzJ1C1pPmGYVoyEtFSAynkruglYv6n3DMgb99O+qfq4lY0Ud7+Byx/Ne1vQj0dV7UACbEffeM9j4x2FtximkF+uOuiAU+2MhK8DjgFWMBUGsIkwICQyKUb8KxXsWfbrWtClCU8YwRvZPi7cmHMwt7momvAnR0XLHXMSW0F7QH5eb4r3khLCIVgUqLlEiLWBj9aL76lVoTZkWohPrEO9SpXbU1mTQfq9JSuz3T32n2wh+oykEcCcxk7tqD1xgA27SWtaOmjpOLr84KfOxJkRobqIgqurx26v5w==|Z1rD6B9mfpUWfVsGCoRJ6i6FSqGk/vD3IlIfNiC+e+A=|10|8094c7f7bd858b74d243d6010c1ee43c&dft=0&uc=1920x1055&pis=-1x-1&sr=1920x1080&tcn=1673247996": 1,
      "http://pagead2.googlesyndication.com/pagead/js/adsbygoogle.js": 20,
      "https://pagead2.googlesyndication.com/pagead/managed/js/adsense/m202301040101/show_ads_impl.js?bust=31071413": 122,
      "https://tpc.googlesyndication.com/sodar/sodar2.js": 61,
      "https://tpc.googlesyndication.com/sodar/sodar2/225/runner.html": 27
    }
  },
  "xd.com": {
    "rank": "996",
    "private": {
      "https://www.xd.com/": 2
    },
    "third": {
      "https://web.xdcdn.net/xd/assets.php?js=%2Fvendor%2Fjs%2Fjquery-1.10.2.min.js%3F1573039035c%2C%2Fjs%2Flayout%2Fxd_unpacked.js%3F1573039034c%2C%2Fvendor%2Frespond%2Fdest%2Frespond.min.js%3F1573039035c%2C%2Fvendor%2Fjquery-placeholder%2Fjquery.placeholder.js%3F1573039034c%2C%2Fvendor%2Fbootstrap-sass%2Fassets%2Fjavascripts%2Fbootstrap%2Ftransition.js%3F1573039034c%2C%2Fvendor%2Fbootstrap-sass%2Fassets%2Fjavascripts%2Fbootstrap%2Faffix.js%3F1573039034c%2C%2Fvendor%2Fbootstrap-sass%2Fassets%2Fjavascripts%2Fbootstrap%2Fbutton.js%3F1573039034c%2C%2Fvendor%2Fbootstrap-sass%2Fassets%2Fjavascripts%2Fbootstrap%2Fcollapse.js%3F1573039034c%2C%2Fvendor%2Fbootstrap-sass%2Fassets%2Fjavascripts%2Fbootstrap%2Fdropdown.js%3F1573039034c%2C%2Fvendor%2Fbootstrap-sass%2Fassets%2Fjavascripts%2Fbootstrap%2Fmodal.js%3F1573039034c%2C%2Fvendor%2Fjquery.lazyload%2Fjquery.lazyload.js%3F1573039035c%2C%2Fjs%2Flayout%2Flottie.js%3F1617003980c%2C%2Fjs%2Flayout%2Fbase_v6.js%3F1617003980c%2C%2Fvendor%2Ffancybox%2Fv3.3.5%2Fjquery.fancybox.min.js%3F1573039034%2C%2Fvendor%2Fxdvideo%2FWebVideo.min.js%3F3%2C%2Fjs%2Fcommon%2Fos.js%3F1617003980%2C%2Fjs%2Fcommon%2FmodalVideoV2.js%3F1617003980%2C%2Fjs%2Fgames_v6%2Fvideo.js%3F1617016990": 32,
      "https://www.google-analytics.com/analytics.js": 13
    }
  },
  "bianfeng.com": {
    "rank": "997",
    "private": {
      "http://www.bianfeng.com/": 1
    },
    "third": {}
  },
  "gotdns.ch": {
    "rank": "998",
    "private": {},
    "third": {
      "http://freeddns.noip.com/?d=www.gotdns.ch&u=d3d3LmdvdGRucy5jaC8=": 9,
      "http://www.google-analytics.com/analytics.js": 46,
      "http://bat.bing.com/bat.js": 2,
      "http://www.googleadservices.com/pagead/conversion.js": 7,
      "http://www.googletagmanager.com/gtm.js?id=GTM-VFGB": 5,
      "https://www.google-analytics.com/gtm/js?id=GTM-K6GQWBT&cid=2050740992.1673242022": 10,
      "https://www.googletagmanager.com/gtag/js?id=G-GG8YBN7FLC": 71,
      "/_/translate_http/_/js/k=translate_http.tr.zh_TW.GiCLTC6gRNo.O/d=1/rs=AN8SPfq4zL35sgXZlBW0mTpxOuR2YKIVYg/m=el_conf": 10,
      "http://cdn.inspectlet.com/inspectlet.js?wid=1629416919&r=464791": 8,
      "https://www.googletagmanager.com/gtag/js?id=UA-31174-1&l=dataLayer&cx=c": 32,
      "https://www.youtube.com/s/player/e5f6cbd5/www-embed-player.vflset/www-embed-player.js": 41,
      "https://www.youtube.com/embed/HHK6bZeLhME?rel=0&autohide=1&showinfo=0&wmode=Opaque&wmode=transparent": 2,
      "https://www.youtube.com/s/player/e5f6cbd5/player_ias.vflset/en_US/base.js": 89,
      "https://www.youtube.com/s/player/e5f6cbd5/player_ias.vflset/en_US/remote.js": 3,
      "about:srcdoc": 1
    }
  },
  "ewsos.com": {
    "rank": "999",
    "private": {
      "http://static.ewsos.com/js/bbb.js": 3,
      "http://static.ewsos.com/js/ewsosinfo.js": 2,
      "http://www.ewsos.com/": 4
    },
    "third": {
      "https://www.youtube.com/s/player/e5f6cbd5/www-embed-player.vflset/www-embed-player.js": 12,
      "https://www.youtube.com/s/player/e5f6cbd5/player_ias.vflset/en_US/base.js": 2,
      "https://cpro.baidustatic.com/cpro/ui/c.js": 91,
      "http://sofire.bdstatic.com/js/dfxaf3-635b4cd6.js": 9,
      "https://pos.baidu.com/hcmm?di=u1564725&uuid=f66e4c9f72555d11&dri=0&dis=0&dai=1&ps=842x0&enu=encoding&exps=110011&ant=0&psi=4c072d21119154fe&dcb=___adblockplus_&dtm=SSP_JSONP&dvi=0.0&dci=-1&dpt=none&tpr=1673248032576&ti=%E5%8C%BB%E7%BD%91_%E5%81%A5%E5%BA%B7%E8%B5%84%E8%AE%AF_%E6%89%BE%E5%8C%BB%E9%99%A2_%E6%89%BE%E5%8C%BB%E7%94%9F_%E4%B8%93%E5%AE%B6%E9%97%AE%E7%AD%94_%E7%96%BE%E7%97%85%E5%A4%A7%E5%85%A8_%E5%B0%B1%E5%8C%BB%E6%8C%87%E5%8D%97_%E5%8C%BB%E7%96%97%E9%97%A8%E6%88%B7%E7%BD%91%E7%AB%99&ari=2&ver=1221&dbv=2&drs=1&pcs=785x585&pss=970x842&cfv=0&cpl=0&chi=50&cce=true&cec=UTF-8&tlm=1673248032&prot=2&rw=600&ltu=http%3A%2F%2Fwww.ewsos.com%2F&ecd=1&dft=0&uc=1920x1055&pis=-1x-1&sr=1920x1080&tcn=1673248033": 1,
      "https://pos.baidu.com/lcum?di=u1564725&uuid=ccc4b49d6d7f698d&dri=3&dis=0&dai=4&ps=4765x0&enu=encoding&exps=110011&ant=0&psi=4c072d21119154fe&dcb=___adblockplus_&dtm=SSP_JSONP&dvi=0.0&dci=-1&dpt=none&tpr=1673248032576&ti=%E5%8C%BB%E7%BD%91_%E5%81%A5%E5%BA%B7%E8%B5%84%E8%AE%AF_%E6%89%BE%E5%8C%BB%E9%99%A2_%E6%89%BE%E5%8C%BB%E7%94%9F_%E4%B8%93%E5%AE%B6%E9%97%AE%E7%AD%94_%E7%96%BE%E7%97%85%E5%A4%A7%E5%85%A8_%E5%B0%B1%E5%8C%BB%E6%8C%87%E5%8D%97_%E5%8C%BB%E7%96%97%E9%97%A8%E6%88%B7%E7%BD%91%E7%AB%99&ari=2&ver=1221&dbv=2&drs=1&pcs=785x585&pss=970x4765&cfv=0&cpl=0&chi=50&cce=true&cec=UTF-8&tlm=1673248032&prot=2&rw=600&ltu=http%3A%2F%2Fwww.ewsos.com%2F&ecd=1&dft=0&uc=1920x1055&pis=-1x-1&sr=1920x1080&tcn=1673248033": 1,
      "https://pos.baidu.com/jcjm?di=u1564725&uuid=b86031731ad31e29&dri=1&dis=0&dai=2&ps=1442x0&enu=encoding&exps=110011&ant=0&psi=4c072d21119154fe&dcb=___adblockplus_&dtm=SSP_JSONP&dvi=0.0&dci=-1&dpt=none&tpr=1673248032576&ti=%E5%8C%BB%E7%BD%91_%E5%81%A5%E5%BA%B7%E8%B5%84%E8%AE%AF_%E6%89%BE%E5%8C%BB%E9%99%A2_%E6%89%BE%E5%8C%BB%E7%94%9F_%E4%B8%93%E5%AE%B6%E9%97%AE%E7%AD%94_%E7%96%BE%E7%97%85%E5%A4%A7%E5%85%A8_%E5%B0%B1%E5%8C%BB%E6%8C%87%E5%8D%97_%E5%8C%BB%E7%96%97%E9%97%A8%E6%88%B7%E7%BD%91%E7%AB%99&ari=2&ver=1221&dbv=2&drs=1&pcs=785x585&pss=970x1442&cfv=0&cpl=0&chi=50&cce=true&cec=UTF-8&tlm=1673248032&prot=2&rw=600&ltu=http%3A%2F%2Fwww.ewsos.com%2F&ecd=1&dft=0&uc=1920x1055&pis=-1x-1&sr=1920x1080&tcn=1673248033": 1,
      "https://pos.baidu.com/ucpm?di=u1564725&uuid=db640105bf6d9af3&dri=2&dis=0&dai=3&ps=4349x0&enu=encoding&exps=110011&ant=0&psi=4c072d21119154fe&dcb=___adblockplus_&dtm=SSP_JSONP&dvi=0.0&dci=-1&dpt=none&tpr=1673248032576&ti=%E5%8C%BB%E7%BD%91_%E5%81%A5%E5%BA%B7%E8%B5%84%E8%AE%AF_%E6%89%BE%E5%8C%BB%E9%99%A2_%E6%89%BE%E5%8C%BB%E7%94%9F_%E4%B8%93%E5%AE%B6%E9%97%AE%E7%AD%94_%E7%96%BE%E7%97%85%E5%A4%A7%E5%85%A8_%E5%B0%B1%E5%8C%BB%E6%8C%87%E5%8D%97_%E5%8C%BB%E7%96%97%E9%97%A8%E6%88%B7%E7%BD%91%E7%AB%99&ari=2&ver=1221&dbv=2&drs=1&pcs=785x585&pss=970x4349&cfv=0&cpl=0&chi=50&cce=true&cec=UTF-8&tlm=1673248032&prot=2&rw=600&ltu=http%3A%2F%2Fwww.ewsos.com%2F&ecd=1&dft=0&uc=1920x1055&pis=-1x-1&sr=1920x1080&tcn=1673248033": 1,
      "https://cpro.baidustatic.com/cpro/ui/f.js": 9,
      "https://pos.baidu.com/hcvm?di=u1564725&uuid=358df924129f2217&dri=4&dis=0&dai=5&ps=9085x0&enu=encoding&exps=110011&ant=0&psi=4c072d21119154fe&dcb=___adblockplus_&dtm=SSP_JSONP&dvi=0.0&dci=-1&dpt=none&tpr=1673248032576&ti=%E5%8C%BB%E7%BD%91_%E5%81%A5%E5%BA%B7%E8%B5%84%E8%AE%AF_%E6%89%BE%E5%8C%BB%E9%99%A2_%E6%89%BE%E5%8C%BB%E7%94%9F_%E4%B8%93%E5%AE%B6%E9%97%AE%E7%AD%94_%E7%96%BE%E7%97%85%E5%A4%A7%E5%85%A8_%E5%B0%B1%E5%8C%BB%E6%8C%87%E5%8D%97_%E5%8C%BB%E7%96%97%E9%97%A8%E6%88%B7%E7%BD%91%E7%AB%99&ari=2&ver=1221&dbv=2&drs=1&pcs=785x585&pss=970x9085&cfv=0&cpl=0&chi=50&cce=true&cec=UTF-8&tlm=1673248032&prot=2&rw=600&ltu=http%3A%2F%2Fwww.ewsos.com%2F&ecd=1&dft=0&uc=1920x1055&pis=-1x-1&sr=1920x1080&tcn=1673248033": 1,
      "https://pos.baidu.com/hcmm?conwid=960&conhei=90&rdid=1564725&dc=3&di=u1564725&s1=3435443357&s2=1837066637&dri=3&dis=0&dai=4&ps=4765x0&enu=encoding&exps=116012,110277,110273,110261,110254,110011&ant=0&psi=4c072d21119154fe&dcb=___adblockplus_&dtm=HTML_POST&dvi=0.0&dci=-1&dpt=none&tpr=1673248032576&ti=%E5%8C%BB%E7%BD%91_%E5%81%A5%E5%BA%B7%E8%B5%84%E8%AE%AF_%E6%89%BE%E5%8C%BB%E9%99%A2_%E6%89%BE%E5%8C%BB%E7%94%9F_%E4%B8%93%E5%AE%B6%E9%97%AE%E7%AD%94_%E7%96%BE%E7%97%85%E5%A4%A7%E5%85%A8_%E5%B0%B1%E5%8C%BB%E6%8C%87%E5%8D%97_%E5%8C%BB%E7%96%97%E9%97%A8%E6%88%B7%E7%BD%91%E7%AB%99&ari=2&ver=1221&dbv=2&drs=1&pcs=785x585&pss=970x4765&cfv=0&cpl=0&chi=50&cce=true&cec=UTF-8&tlm=1673248032&prot=2&rw=600&ltu=http%3A%2F%2Fwww.ewsos.com%2F&ecd=1&dft=0&uc=1920x1055&pis=-1x-1&sr=1920x1080&tcn=1673248033&qn=f99ba8dee6cf0369&ft=1": 23,
      "https://cpro.baidustatic.com/js/logo/js/logo.js": 16,
      "https://pos.baidu.com/hcmm?conwid=960&conhei=90&rdid=1564725&dc=3&di=u1564725&s1=898496804&s2=312418839&dri=4&dis=0&dai=5&ps=9085x0&enu=encoding&exps=110277,110273,110261,110254,110011&ant=0&psi=4c072d21119154fe&dcb=___adblockplus_&dtm=HTML_POST&dvi=0.0&dci=-1&dpt=none&tpr=1673248032576&ti=%E5%8C%BB%E7%BD%91_%E5%81%A5%E5%BA%B7%E8%B5%84%E8%AE%AF_%E6%89%BE%E5%8C%BB%E9%99%A2_%E6%89%BE%E5%8C%BB%E7%94%9F_%E4%B8%93%E5%AE%B6%E9%97%AE%E7%AD%94_%E7%96%BE%E7%97%85%E5%A4%A7%E5%85%A8_%E5%B0%B1%E5%8C%BB%E6%8C%87%E5%8D%97_%E5%8C%BB%E7%96%97%E9%97%A8%E6%88%B7%E7%BD%91%E7%AB%99&ari=2&ver=1221&dbv=2&drs=1&pcs=785x585&pss=970x9085&cfv=0&cpl=0&chi=50&cce=true&cec=UTF-8&tlm=1673248032&prot=2&rw=600&ltu=http%3A%2F%2Fwww.ewsos.com%2F&ecd=1&dft=0&uc=1920x1055&pis=-1x-1&sr=1920x1080&tcn=1673248033&qn=ba45d300575c77b1&ft=1": 29,
      "https://pos.baidu.com/hcmm?conwid=960&conhei=90&rdid=1564725&dc=3&di=u1564725&s1=4134423711&s2=1918197009&dri=0&dis=0&dai=1&ps=842x0&enu=encoding&exps=110277,110273,110261,110254,110011&ant=0&psi=4c072d21119154fe&dcb=___adblockplus_&dtm=HTML_POST&dvi=0.0&dci=-1&dpt=none&tpr=1673248032576&ti=%E5%8C%BB%E7%BD%91_%E5%81%A5%E5%BA%B7%E8%B5%84%E8%AE%AF_%E6%89%BE%E5%8C%BB%E9%99%A2_%E6%89%BE%E5%8C%BB%E7%94%9F_%E4%B8%93%E5%AE%B6%E9%97%AE%E7%AD%94_%E7%96%BE%E7%97%85%E5%A4%A7%E5%85%A8_%E5%B0%B1%E5%8C%BB%E6%8C%87%E5%8D%97_%E5%8C%BB%E7%96%97%E9%97%A8%E6%88%B7%E7%BD%91%E7%AB%99&ari=2&ver=1221&dbv=2&drs=1&pcs=785x585&pss=970x842&cfv=0&cpl=0&chi=50&cce=true&cec=UTF-8&tlm=1673248032&prot=2&rw=600&ltu=http%3A%2F%2Fwww.ewsos.com%2F&ecd=1&dft=0&uc=1920x1055&pis=-1x-1&sr=1920x1080&tcn=1673248033&qn=560a6ee7b47294c7&ft=1": 29,
      "https://pos.baidu.com/hcmm?conwid=960&conhei=90&rdid=1564725&dc=3&di=u1564725&s1=3680764165&s2=3211631347&dri=2&dis=0&dai=3&ps=4349x0&enu=encoding&exps=110277,110273,110261,110254,110011&ant=0&psi=4c072d21119154fe&dcb=___adblockplus_&dtm=HTML_POST&dvi=0.0&dci=-1&dpt=none&tpr=1673248032576&ti=%E5%8C%BB%E7%BD%91_%E5%81%A5%E5%BA%B7%E8%B5%84%E8%AE%AF_%E6%89%BE%E5%8C%BB%E9%99%A2_%E6%89%BE%E5%8C%BB%E7%94%9F_%E4%B8%93%E5%AE%B6%E9%97%AE%E7%AD%94_%E7%96%BE%E7%97%85%E5%A4%A7%E5%85%A8_%E5%B0%B1%E5%8C%BB%E6%8C%87%E5%8D%97_%E5%8C%BB%E7%96%97%E9%97%A8%E6%88%B7%E7%BD%91%E7%AB%99&ari=2&ver=1221&dbv=2&drs=1&pcs=785x585&pss=970x4349&cfv=0&cpl=0&chi=50&cce=true&cec=UTF-8&tlm=1673248032&prot=2&rw=600&ltu=http%3A%2F%2Fwww.ewsos.com%2F&ecd=1&dft=0&uc=1920x1055&pis=-1x-1&sr=1920x1080&tcn=1673248033&qn=089c33b36daa3cec&ft=1": 29
    }
  },
  "emoney.cn": {
    "rank": "1000",
    "private": {
      "http://www.emoney.cn/static/js/advert.js": 4,
      "https://static-dsclient.emoney.cn/emvplayer/normal/videoMediaSDKnew.html?midtype=vod&uid=&pid=null&appid=&voteid=0&uname=&authcode=888888&ischeckpwd=0&courseid=0&bztype=&ownerid=42bf67f8177744c8a2b762a6ac42dfa9&rep=1&py=1": 3,
      "http://www.emoney.cn/": 2
    },
    "third": {
      "https://dup.baidustatic.com/js/os.js": 17,
      "http://sofire.bdstatic.com/js/dfxaf3-635b4cd6.js": 9,
      "https://static.gensee.com/webcast/static/sdk/js/gssdk-1.3.js?1673248045693": 17,
      "https://emoney.gensee.com/sdk/site/sdk/h5/vod?widgetid=videoComponent&id=videoComponent&site=emoney.gensee.com&bgimg=https%3A%2F%2Fedf.emoney.cn%2Femoney%2FM00%2F01%2F18%2FrBwBVmFRXLmACC-PAACyX1QW39I374.jpg&ctx=webcast&fullscreen=true&ownerid=42bf67f8177744c8a2b762a6ac42dfa9&uid=&uname=%E7%AD%96%E7%95%A5%E5%A4%A7%E7%9B%B4%E6%92%AD%EF%BC%9A%3Anull&authcode=888888&bar=true&gsver=2&py=1&class=gs-sdk-widget&jsonpcallback=__GSJsonp.jsonpcallback_0": 4,
      "https://static.gensee.com/webcast/static/sdk/js/gensee-common.js?20221101071615": 8,
      "https://static.gensee.com/webcast/static/sdk/js/gensee-vod.js?20221101071615": 8
    }
  }
}